setup.py
codecov/__init__.py
codecov/clover.py
codecov/cobertura.py
codecov/jacoco.py
robpol86_codecov.egg-info/PKG-INFO
robpol86_codecov.egg-info/SOURCES.txt
robpol86_codecov.egg-info/dependency_links.txt
robpol86_codecov.egg-info/entry_points.txt
robpol86_codecov.egg-info/requires.txt
robpol86_codecov.egg-info/top_level.txt
robpol86_codecov.egg-info/zip-safe