Metadata-Version: 1.1
Name: robpol86-codecov
Version: 1.1.8
Summary: Temporary fork of codecov-python.
Home-page: http://github.com/codecov/codecov-python
Author: @codecov
Author-email: hello@codecov.io
License: http://www.apache.org/licenses/LICENSE-2.0
Keywords: coverage codecov code python java scala php
Platform: UNKNOWN
Classifier: Development Status :: 4 - Beta
Classifier: Environment :: Plugins
Classifier: Intended Audience :: Developers
Classifier: Programming Language :: Python
Classifier: Programming Language :: Python :: 2.7
Classifier: Programming Language :: Python :: 3
Classifier: Programming Language :: Python :: 3.4
Classifier: Programming Language :: Python :: Implementation :: PyPy
Classifier: License :: OSI Approved :: Apache Software License
Classifier: Topic :: Software Development :: Testing
